Workbook

Sheet data-analysis
A2: LEGO created each year with number of parts of that LEGO set | E2: LEGO Sets created each year( exclude 2020 and 2021) | H2: top 10 LEGO sets with total number of parts created ( taj mahal 2008 + taj mahal 2017) | K2: top 10 LEGO sets with most number of parts (single unit)
A3: year | B3: name | C3: Sum of num_parts | E3: year | F3: Count of name | H3: name | I3: Sum of num_parts | K3: name | L3: Max of num_parts
A4: 1949 | B4: Large Gift Set (ABB) | C4: 178 | E4: 1949 | F4: 5 | H4: Basic Building Set | I4: 11954 | K4: The Ultimate Battle for Chima | L4: 9987
B5: Extra-Large Gift Set (ABB) | C5: 142 | E5: 1950 | F5: 6 | H5: Taj Mahal | I5: 11845 | K5: UCS Millennium Falcon | L5: 7541
B6: Medium Gift Set (ABB) | C6: 142 | E6: 1953 | F6: 4 | H6: The Ultimate Battle for Chima | I6: 9987 | K6: Hogwarts Castle | L6: 6020
B7: Small Brick Set (ABB) | C7: 24 | E7: 1954 | F7: 14 | H7: Hogwarts Castle | I7: 9887 | K7: Taj Mahal | L7: 5923
B8: Small Doors and Windows Set (ABB) | C8: 12 | E8: 1955 | F8: 28 | H8: Universal Building Set | I8: 8719 | K8: Diagon Alley | L8: 5547
A9: 1950 | B9: Single 1 x 4 x 2 Window without Glass (ABB) | C9: 1 | E9: 1956 | F9: 13 | H9: Diagon Alley | I9: 7952 | K9: Star Wars / M&M Mosaic - Promo Set | L9: 5462
B10: Single 2 x 4 Brick (ABB) | C10: 1 | E10: 1957 | F10: 20 | H10: Death Star | I10: 7838 | K10: Window Exploration Bag | L10: 5200
B11: Single 2 x 2 Brick (ABB) | C11: 1 | E11: 1958 | F11: 46 | H11: UCS Millennium Falcon | I11: 7541 | K11: Millennium Falcon - UCS | L11: 5195
B12: Single 1 x 2 x 3 Window without Glass (ABB) | C12: 1 | E12: 1959 | F12: 4 | H12: Imperial Star Destroyer | I12: 7531 | K12: NINJAGO City | L12: 4873
B13: Single 1 x 2 x 2 Window without Glass (ABB) | C13: 1 | E13: 1960 | F13: 3 | H13: Sandcrawler | I13: 6265 | K13: Imperial Star Destroyer | L13: 4784
B14: Single 1 x 2 x 4 Door without Glass (ABB) | C14: 1 | E14: 1961 | F14: 22 | H14: Grand Total | I14: 89519 | K14: Grand Total | L14: 9987
A15: 1953 | B15: Automatic Binding Bricks - Small Brick Set (Lego Mursten) | C15: 48 | E15: 1962 | F15: 41
B16: Individual 2 x 3 Bricks | C16: 5 | E16: 1963 | F16: 20
B17: Individual 1 x 2 Bricks | C17: 1 | E17: 1964 | F17: 18
B18: Extra-Large Gift Set (Mursten) | C18: 0 | E18: 1965 | F18: 13
A19: 1954 | B19: Gift Package (Lego Mursten) | C19: 100 | E19: 1966 | F19: 111
B20: Tall Classic Windows/Door (with Glass) | C20: 24 | E20: 1967 | F20: 28
B21: Individual 2 x 12 Bricks | C21: 5 | E21: 1968 | F21: 39
B22: Individual 2 x 10 Bricks | C22: 5 | E22: 1969 | F22: 81
B23: Individual 2 x 14 Bricks | C23: 5 | E23: 1970 | F23: 37
B24: Individual 2 x 8 Bricks | C24: 5 | E24: 1971 | F24: 51
B25: Individual 4 x 4 Corner Bricks | C25: 5 | E25: 1972 | F25: 39
B26: Individual 1 x 6 x 3 3-Pane Window (with glass) | C26: 4 | E26: 1973 | F26: 70
B27: Individual 1 x 3 x 3 Window (with glass) | C27: 4 | E27: 1974 | F27: 39
B28: Individual 1 x 4 x 3 Window (with glass) | C28: 4 | E28: 1975 | F28: 39
B29: Individual 1 x 2 x 4 Door (with glass) | C29: 4 | E29: 1976 | F29: 76
B30: Individual 1 x 6 x 3 Shutter Window (with glass) | C30: 4 | E30: 1977 | F30: 99
B31: Individual 1 x 6 x 4 Panorama Window (with glass) | C31: 4 | E31: 1978 | F31: 78
A32: 1955 | B32: 1 x 1 Round Bricks | C32: 200 | E32: 1979 | F32: 92
B33: 1 x 1 Bricks | C33: 160 | E33: 1980 | F33: 102
B34: 1 x 2 Bricks | C34: 104 | E34: 1981 | F34: 84
B35: 2 x 2 Bricks | C35: 80 | E35: 1982 | F35: 84
B36: 2 x 3 Bricks | C36: 60 | E36: 1983 | F36: 73
B37: Garage | C37: 59 | E37: 1984 | F37: 95
B38: 2 x 4 Bricks | C38: 52 | E38: 1985 | F38: 168
B39: Lego Mosaik Set (Small) | C39: 47 | E39: 1986 | F39: 159
B40: 1 x 6 and 1 x 8 Bricks | C40: 36 | E40: 1987 | F40: 233
B41: Small Store Set | C41: 30 | E41: 1988 | F41: 80
B42: Windows and Doors | C42: 24 | E42: 1989 | F42: 134
B43: Small House - Right Set | C43: 23 | E43: 1990 | F43: 108
B44: Small House - Left Set | C44: 21 | E44: 1991 | F44: 148
... B58: Lego Mursten - System i Leg Byggebog | C58: 0 | E58: 2005 | F58: 351
A59: 1956 | B59: ESSO Filling Station | C59: 96 | E59: 2006 | F59: 313
B60: Garage with Automatic Door (White base and door frame) | C60: 69 | E60: 2007 | F60: 315
B61: 2 x 8 Mursten Bricks (EUR) | C61: 24 | E61: 2008 | F61: 341
B62: 2 x 2 & 2 x 4 Curved Bricks | C62: 14 | E62: 2009 | F62: 421
B63: Windows and Door with Glass, Red | C63: 10 | E63: 2010 | F63: 435
B64: Windows and Door with Glass, White | C64: 10 | E64: 2011 | F64: 503
B65: Traffic Police Set | C65: 6 | E65: 2012 | F65: 607
B66: 4 x 8 & 2 x 8 Plates | C66: 5 | E66: 2013 | F66: 605
B67: 4 x 8 Curved & 2 x 8 Plates | C67: 5 | E67: 2014 | F67: 690
B68: 6 x 8 & 2 x 8 Plates | C68: 4 | E68: 2015 | F68: 774
B69: Esso Pumps/Sign | C69: 2 | E69: 2016 | F69: 757
B70: LEGO Town Plan Board, Small Plastic | C70: 1 | E70: 2017 | F70: 786
B71: System im Spiel | C71: 0 | E71: 2018 | F71: 816
A72: 1957 | B72: Gift Package | C72: 290 | E72: 2019 | F72: 840
B73: Church | C73: 150 | E73: Grand Total | F73: 15033
B74: Fire Station | C74: 109
B75: 2 x 2 Curved Bricks | C75: 100
B76: Garage and Van | C76: 69
B77: VW Auto Showroom | C77: 51 | E77: average num of parts per year | H77: scatter graph can't be plotted in pivot table data
B78: VW Garage | C78: 45 | E78: year | F78: Average of num_parts | H78: year | I78: avg num of parts
B79: 1:87 Twenty Four Models | C79: 24 | E79: 1949 | F79: 99.6 | H79: =E79 -> 1949 | I79: =GETPIVOTDATA("num_parts",$E$78,"year",E79) -> 99.6
B80: Sloping Ridge and Valley Bricks, Blue | C80: 20 | E80: 1950 | F80: 1 | H80: =E80 -> 1950 | I80: =GETPIVOTDATA("num_parts",$E$78,"year",E80) -> 1
B81: Sloping Ridge and Valley Bricks, Red | C81: 20 | E81: 1953 | F81: 13.5 | H81: =E81 -> 1953 | I81: =GETPIVOTDATA("num_parts",$E$78,"year",E81) -> 13.5
B82: 5 Danish Flags | C82: 5 | E82: 1954 | F82: 12.357143 | H82: =E82 -> 1954 | I82: =GETPIVOTDATA("num_parts",$E$78,"year",E82) -> 12.357143
B83: International Flags | C83: 5 | E83: 1955 | F83: 36.607143 | H83: =E83 -> 1955 | I83: =GETPIVOTDATA("num_parts",$E$78,"year",E83) -> 36.607143
B84: LEGO Town Plan Wooden Board | C84: 3 | E84: 1956 | F84: 18.923077 | H84: =E84 -> 1956 | I84: =GETPIVOTDATA("num_parts",$E$78,"year",E84) -> 18.923077
B85: Lighting Device Pack | C85: 3 | E85: 1957 | F85: 44.75 | H85: =E85 -> 1957 | I85: =GETPIVOTDATA("num_parts",$E$78,"year",E85) -> 44.75
B86: LEGO Town Plan Board, Plastic | C86: 1 | E86: 1958 | F86: 41.130435 | H86: =E86 -> 1958 | I86: =GETPIVOTDATA("num_parts",$E$78,"year",E86) -> 41.130435
A87: 1958 | B87: 1 x 1 Bricks | C87: 240 | E87: 1959 | F87: 16.25 | H87: =E87 -> 1959 | I87: =GETPIVOTDATA("num_parts",$E$78,"year",E87) -> 16.25
B88: 1 x 1 Round Bricks | C88: 160 | E88: 1960 | F88: 175.33333 | H88: =E88 -> 1960 | I88: =GETPIVOTDATA("num_parts",$E$78,"year",E88) -> 175.33333
B89: 1 x 2 Bricks | C89: 156 | E89: 1961 | F89: 58.227273 | H89: =E89 -> 1961 | I89: =GETPIVOTDATA("num_parts",$E$78,"year",E89) -> 58.227273
B90: Church | C90: 149 | E90: 1962 | F90: 79.97561 | H90: =E90 -> 1962 | I90: =GETPIVOTDATA("num_parts",$E$78,"year",E90) -> 79.97561
B91: 2 x 2 Curved Bricks | C91: 120 | E91: 1963 | F91: 47 | H91: =E91 -> 1963 | I91: =GETPIVOTDATA("num_parts",$E$78,"year",E91) -> 47
B92: 2 x 2 Bricks | C92: 120 | E92: 1964 | F92: 79.166667 | H92: =E92 -> 1964 | I92: =GETPIVOTDATA("num_parts",$E$78,"year",E92) -> 79.166667
B93: Fire Station | C93: 111 | E93: 1965 | F93: 86 | H93: =E93 -> 1965 | I93: =GETPIVOTDATA("num_parts",$E$78,"year",E93) -> 86
B94: ESSO Filling Station | C94: 96 | E94: 1966 | F94: 46.72973 | H94: =E94 -> 1966 | I94: =GETPIVOTDATA("num_parts",$E$78,"year",E94) -> 46.72973
B95: 2 x 3 Bricks | C95: 90 | E95: 1967 | F95: 121.75 | H95: =E95 -> 1967 | I95: =GETPIVOTDATA("num_parts",$E$78,"year",E95) -> 121.75
B96: 2 x 4 Bricks | C96: 78 | E96: 1968 | F96: 116.4359 | H96: =E96 -> 1968 | I96: =GETPIVOTDATA("num_parts",$E$78,"year",E96) -> 116.4359
B97: 1 x 6 and 1 x 8 Bricks | C97: 54 | E97: 1969 | F97: 74.641975 | H97: =E97 -> 1969 | I97: =GETPIVOTDATA("num_parts",$E$78,"year",E97) -> 74.641975
B98: Letter Bricks | C98: 53 | E98: 1970 | F98: 81.675676 | H98: =E98 -> 1970 | I98: =GETPIVOTDATA("num_parts",$E$78,"year",E98) -> 81.675676
B99: VW Auto Showroom | C99: 51 | E99: 1971 | F99: 77.196078 | H99: =E99 -> 1971 | I99: =GETPIVOTDATA("num_parts",$E$78,"year",E99) -> 77.196078
... B130: Bricks Box | C130: 2 | E130: 2002 | F130: 107.30952 | H130: =E130 -> 2002 | I130: =GETPIVOTDATA("num_parts",$E$78,"year",E130) -> 107.30952
A131: 1959 | B131: Volkswagen Kit | C131: 22 | E131: 2003 | F131: 157.06803 | H131: =E131 -> 2003 | I131: =GETPIVOTDATA("num_parts",$E$78,"year",E131) -> 157.06803
B132: 1 x 2 and 3 x 2 Sloping Bricks, Blue | C132: 21 | E132: 2004 | F132: 141.5519 | H132: =E132 -> 2004 | I132: =GETPIVOTDATA("num_parts",$E$78,"year",E132) -> 141.5519
B133: 1 x 2 and 3 x 2 Sloping Bricks, Red | C133: 21 | E133: 2005 | F133: 196.53561 | H133: =E133 -> 2005 | I133: =GETPIVOTDATA("num_parts",$E$78,"year",E133) -> 196.53561
B134: LEGO Town Plan Board, Continental European Cardboard Version | C134: 1 | E134: 2006 | F134: 236.61981 | H134: =E134 -> 2006 | I134: =GETPIVOTDATA("num_parts",$E$78,"year",E134) -> 236.61981
A135: 1960 | B135: Kindergarten LEGO Set | C135: 476 | E135: 2007 | F135: 242.6381 | H135: =E135 -> 2007 | I135: =GETPIVOTDATA("num_parts",$E$78,"year",E135) -> 242.6381
B136: Number Bricks | C136: 50 | E136: 2008 | F136: 244.01466 | H136: =E136 -> 2008 | I136: =GETPIVOTDATA("num_parts",$E$78,"year",E136) -> 244.01466
B137: Lego System Idea Book no. 1 | C137: 0 | E137: 2009 | F137: 195.39667 | H137: =E137 -> 2009 | I137: =GETPIVOTDATA("num_parts",$E$78,"year",E137) -> 195.39667
A138: 1961 | B138: Town Plan - Continental European | C138: 760 | E138: 2010 | F138: 216.78391 | H138: =E138 -> 2010 | I138: =GETPIVOTDATA("num_parts",$E$78,"year",E138) -> 216.78391
B139: Boats | C139: 107 | E139: 2011 | F139: 161.89463 | H139: =E139 -> 2011 | I139: =GETPIVOTDATA("num_parts",$E$78,"year",E139) -> 161.89463
B140: Airplanes | C140: 79 | E140: 2012 | F140: 154.15321 | H140: =E140 -> 2012 | I140: =GETPIVOTDATA("num_parts",$E$78,"year",E140) -> 154.15321
B141: 2 x 8 Bricks (USA/CAN) | C141: 45 | E141: 2013 | F141: 180.0314 | H141: =E141 -> 2013 | I141: =GETPIVOTDATA("num_parts",$E$78,"year",E141) -> 180.0314
B142: 1 x 1 x 1 Window Frame | C142: 40 | E142: 2014 | F142: 179.91159 | H142: =E142 -> 2014 | I142: =GETPIVOTDATA("num_parts",$E$78,"year",E142) -> 179.91159
B143: 1 x 2 x 1 Window Frame | C143: 38 | E143: 2015 | F143: 191.37984 | H143: =E143 -> 2015 | I143: =GETPIVOTDATA("num_parts",$E$78,"year",E143) -> 191.37984
B144: 1 x 1 x 2 Window Frame | C144: 38 | E144: 2016 | F144: 209.92074 | H144: =E144 -> 2016 | I144: =GETPIVOTDATA("num_parts",$E$78,"year",E144) -> 209.92074
...

Sheet themes_per_year
A1: to activate Distinct count: when we create our pivot table, we are going to check the box that says Add this table to the Data Model. (Data Model is another term for PowerPivot.)
A2: for distinct count go to Value Field Settings
A4: number of themes per year (till 2019) | F4: Top 10 themes with largest number of sets
A5: Row Labels | B5: Distinct Count of theme_id | C5: num of sets per year | F5: Theme id | G5: Count of set_num | H5: Theme Name using vlookup
A6: 1949 | B6: 2 | C6: 5 | F6: 158 | G6: 753 | H6: =VLOOKUP(F6,'Themes-name-data'!$A$2:$N$598,2,FALSE) -> Star Wars
A7: 1950 | B7: 1 | C7: 6 | F7: 501 | G7: 656 | H7: =VLOOKUP(F7,'Themes-name-data'!$A$2:$N$598,2,FALSE) -> Gear
A8: 1953 | B8: 2 | C8: 4 | F8: 494 | G8: 398 | H8: =VLOOKUP(F8,'Themes-name-data'!$A$2:$N$598,2,FALSE) -> Friends
A9: 1954 | B9: 2 | C9: 14 | F9: 435 | G9: 356 | H9: =VLOOKUP(F9,'Themes-name-data'!$A$2:$N$598,2,FALSE) -> Ninjago
A10: 1955 | B10: 4 | C10: 28 | F10: 503 | G10: 329 | H10: =VLOOKUP(F10,'Themes-name-data'!$A$2:$N$598,2,FALSE) -> Key Chain
A11: 1956 | B11: 3 | C11: 13 | F11: 505 | G11: 328 | H11: =VLOOKUP(F11,'Themes-name-data'!$A$2:$N$598,2,FALSE) -> Basic Set
A12: 1957 | B12: 4 | C12: 20 | F12: 497 | G12: 310 | H12: =VLOOKUP(F12,'Themes-name-data'!$A$2:$N$598,2,FALSE) -> Books
A13: 1958 | B13: 3 | C13: 46 | F13: 632 | G13: 299 | H13: =VLOOKUP(F13,'Themes-name-data'!$A$2:$N$598,2,FALSE) -> Town
A14: 1959 | B14: 3 | C14: 4 | F14: 371 | G14: 273 | H14: =VLOOKUP(F14,'Themes-name-data'!$A$2:$N$598,2,FALSE) -> Supplemental
A15: 1960 | B15: 3 | C15: 3 | F15: 516 | G15: 248 | H15: =VLOOKUP(F15,'Themes-name-data'!$A$2:$N$598,2,FALSE) -> Duplo and Explore
A16: 1961 | B16: 6 | C16: 22
A17: 1962 | B17: 4 | C17: 41
A18: 1963 | B18: 8 | C18: 20
A19: 1964 | B19: 9 | C19: 18
A20: 1965 | B20: 8 | C20: 13
A21: 1966 | B21: 13 | C21: 111
A22: 1967 | B22: 12 | C22: 28
A23: 1968 | B23: 16 | C23: 39
A24: 1969 | B24: 18 | C24: 81
A25: 1970 | B25: 18 | C25: 37
A26: 1971 | B26: 14 | C26: 51
A27: 1972 | B27: 13 | C27: 39
... A74: 2019 | B74: 78 | C74: 840
A75: Grand Total | B75: 561 | C75: 15033

Sheet Themes-name-data
A1: id | B1: name | C1: parent_id
A2: 1 | B2: Technic
A3: 2 | B3: Arctic Technic | C3: 1 | G3: columns which has name star wars( advance filtering)
A4: 3 | B4: Competition | C4: 1 | G4: name
A5: 4 | B5: Expert Builder | C5: 1 | G5: Star Wars
A6: 5 | B6: Model | C6: 1 | I6: id | J6: name | K6: parent_id
A7: 6 | B7: Airport | C7: 5 | I7: 18 | J7: Star Wars | K7: 1
A8: 7 | B8: Construction | C8: 5 | I8: 158 | J8: Star Wars
A9: 8 | B9: Farm | C9: 5 | I9: 209 | J9: Star Wars | K9: 207
A10: 9 | B10: Fire | C10: 5 | I10: 261 | J10: Star Wars | K10: 258
A11: 10 | B11: Harbor | C11: 5
A12: 11 | B12: Off-Road | C12: 5
A13: 12 | B13: Race | C13: 5
A14: 13 | B14: Riding Cycle | C14: 5 | G14: check which products corresponded to those star wars themes in the sets data
A15: 14 | B15: Robot | C15: 5
A16: 15 | B16: Traffic | C16: 5
A17: 16 | B17: RoboRiders | C17: 1
A18: 17 | B18: Speed Slammers | C18: 1
A19: 18 | B19: Star Wars | C19: 1
A20: 19 | B20: Supplemental | C20: 1
A21: 20 | B21: Throwbot Slizer | C21: 1
A22: 21 | B22: Universal Building Set | C22: 1
A23: 22 | B23: Creator
A24: 23 | B24: Basic Model | C24: 22
A25: 24 | B25: Airport | C25: 23
A26: 25 | B26: Castle | C26: 23
A27: 26 | B27: Construction | C27: 23
A28: 27 | B28: Race | C28: 23
A29: 28 | B29: Harbor | C29: 23
A30: 29 | B30: Train | C30: 23
A31: 30 | B31: Traffic | C31: 23
A32: 31 | B32: Creature | C32: 23
A33: 32 | B33: Robot | C33: 23
A34: 33 | B34: Food & Drink | C34: 23
A35: 34 | B35: Building | C35: 23
... A47: 49 | B47: Mecha | C47: 22
A48: 50 | B48: Town
A49: 51 | B49: Arctic | C49: 50
A50: 52 | B50: City | C50: 50
A51: 53 | B51: Airport | C51: 52
A52: 54 | B52: Cargo | C52: 52
A53: 55 | B53: Coast Guard | C53: 52
A54: 56 | B54: Construction | C54: 52
A55: 57 | B55: Farm | C55: 52
A56: 58 | B56: Fire | C56: 52
A57: 59 | B57: Harbor | C57: 52
A58: 60 | B58: Hospital | C58: 52
A59: 61 | B59: Police | C59: 52
A60: 62 | B60: Supplemental | C60: 52
... A107: 111 | B107: Police | C107: 105
A108: 112 | B108: Racers
A109: 113 | B109: Drome Racers | C109: 112
A110: 114 | B110: Ferrari | C110: 112
A111: 115 | B111: Lamborghini | C111: 112
A112: 116 | B112: Power Racers | C112: 112
A113: 117 | B113: Radio Control | C113: 112
A114: 118 | B114: Speed Racer | C114: 112
A115: 119 | B115: Supplemental | C115: 112
A116: 120 | B116: Tiny Turbos | C116: 112
A117: 121 | B117: Track System | C117: 112
A118: 122 | B118: Williams F1 | C118: 112
A119: 123 | B119: World Racers | C119: 112
A120: 125 | B120: Xalax | C120: 112
A121: 126 | B121: Space
A122: 127 | B122: Alien Conquest | C122: 126
A123: 128 | B123: Blacktron I | C123: 126
A124: 129 | B124: Blacktron II | C124: 126
A125: 130 | B125: Classic Space | C125: 126
A126: 131 | B126: Exploriens | C126: 126
A127: 132 | B127: Futuron | C127: 126
A128: 133 | B128: Ice Planet 2002 | C128: 126
A129: 134 | B129: Insectoids | C129: 126
A130: 135 | B130: Life On Mars | C130: 126
A131: 136 | B131: M:Tron | C131: 126
A132: 137 | B132: Mars Mission | C132: 126
A133: 138 | B133: RoboForce | C133: 126
... A141: 146 | B141: Galaxy Squad | C141: 126
A142: 147 | B142: Pirates
A143: 148 | B143: Pirates I | C143: 147
A144: 149 | B144: Imperial Armada | C144: 148
A145: 151 | B145: Imperial Soldiers | C145: 148
A146: 152 | B146: Islanders | C146: 148
A147: 153 | B147: Pirates II | C147: 147
A148: 154 | B148: Pirates III | C148: 147
A149: 155 | B149: Modular Buildings
A150: 156 | B150: Mini | C150: 155
A151: 157 | B151: Bricktober | C151: 155
A152: 158 | B152: Star Wars
A153: 171 | B153: Ultimate Collector Series | C153: 158
A154: 186 | B154: Castle
A155: 187 | B155: Black Falcons | C155: 186
A156: 188 | B156: Black Knights | C156: 186
A157: 189 | B157: Classic Castle | C157: 186
A158: 190 | B158: Crusaders | C158: 186
A159: 191 | B159: Dark Forest | C159: 186
A160: 193 | B160: Fantasy Era | C160: 186
A161: 194 | B161: Forestmen | C161: 186
A162: 195 | B162: Fright Knights | C162: 186
A163: 196 | B163: Kingdoms | C163: 186
A164: 197 | B164: Knights Kingdom I | C164: 186
...

Sheet sets-data
A1: set_num | B1: name | C1: year | D1: theme_id | E1: num_parts
A2: 700.1-1 | B2: Extra-Large Gift Set (ABB) | C2: 1949 | D2: 365 | E2: 142
A3: 700.2-1 | B3: Large Gift Set (ABB) | C3: 1949 | D3: 365 | E3: 178
A4: 700.3-1 | B4: Medium Gift Set (ABB) | C4: 1949 | D4: 365 | E4: 142
A5: 700.A-1 | B5: Small Brick Set (ABB) | C5: 1949 | D5: 371 | E5: 24
A6: 700.B-1 | B6: Small Doors and Windows Set (ABB) | C6: 1949 | D6: 371 | E6: 12
A7: 700.1.1-1 | B7: Single 2 x 4 Brick (ABB) | C7: 1950 | D7: 371 | E7: 1
A8: 700.1.2-1 | B8: Single 2 x 2 Brick (ABB) | C8: 1950 | D8: 371 | E8: 1
A9: 700.B.1-1 | B9: Single 1 x 4 x 2 Window without Glass (ABB) | C9: 1950 | D9: 371 | E9: 1
A10: 700.B.2-1 | B10: Single 1 x 2 x 3 Window without Glass (ABB) | C10: 1950 | D10: 371 | E10: 1
A11: 700.B.3-1 | B11: Single 1 x 2 x 2 Window without Glass (ABB) | C11: 1950 | D11: 371 | E11: 1
A12: 700.B.4-1 | B12: Single 1 x 2 x 4 Door without Glass (ABB) | C12: 1950 | D12: 371 | E12: 1
A13: 700.1.4-1 | B13: Individual 1 x 2 Bricks | C13: 1953 | D13: 371 | E13: 1
... A369: b66de-01 | B369: LEGO Motor Eisenbahn | C369: 1966 | D369: 499 | E369: 0
A370: 45692 | B370: Velveeta Set No. 4 with Carrying Case | C370: 1967 | D370: 366 | E370: 283
A371: 45693 | B371: Velveeta Set No. 5 | C371: 1967 | D371: 371 | E371: 20
A372: 45717 | B372: Velveeta Set No. 1 | C372: 1967 | D372: 366 | E372: 74
A373: 005-2 | B373: Discovery Set | C373: 1967 | D373: 366 | E373: 0
A374: 080-1 | B374: Basic Building Set with Train | C374: 1967 | D374: 366 | E374: 712
A375: 080-2 | B375: Ambassador Set | C375: 1967 | D375: 366 | E375: 712
A376: 116-1 | B376: Starter Train Set with Motor | C376: 1967 | D376: 235 | E376: 364
A377: 117-1 | B377: Locomotive without Motor | C377: 1967 | D377: 235 | E377: 99
A378: 154-1 | B378: Switch Track - 1 Right and 1 Left | C378: 1967 | D378: 243 | E378: 4
A379: 155-1 | B379: 2 Cross Rails, 8 Straight Tracks, 4 Base Plates | C379: 1967 | D379: 243 | E379: 14
A380: 240-1 | B380: Wooden Storage Box Large, Empty | C380: 1967 | D380: 383 | E380: 0
A381: 240-2 | B381: Idea Book | C381: 1967 | D381: 497 | E381: 1
A382: 328-2 | B382: Biplane | C382: 1967 | D382: 374 | E382: 44
A383: 329-1 | B383: Antique Car | C383: 1967 | D383: 378 | E383: 111
A384: 331-1 | B384: Dump Truck | C384: 1967 | D384: 381 | E384: 45
... A517: LIFECEREAL-1 | B517: Puppet Set | C517: 1969 | D517: 598 | E517: 92
A518: 45751 | B518: Large House Set | C518: 1970 | D518: 433 | E518: 218
A519: 45811 | B519: Medium House Set | C519: 1970 | D519: 433 | E519: 158
A520: 45870 | B520: Little House Set | C520: 1970 | D520: 433 | E520: 67
A521: 45871 | B521: Medium House Set | C521: 1970 | D521: 433 | E521: 109
A522: 078-1 | B522: Roadway Base Plate | C522: 1970 | D522: 371 | E522: 0
A523: 102A-1 | B523: Front-End Loader | C523: 1970 | D523: 416 | E523: 64
A524: 102A-2 | B524: Front-End Loader | C524: 1970 | D524: 416 | E524: 56
A525: 104-1 | B525: Replacement 4.5V Motor | C525: 1970 | D525: 243 | E525: 1
A526: 126-1 | B526: Steam Locomotive (Push) | C526: 1970 | D526: 235 | E526: 60
A527: 157-3 | B527: Four Car Auto Transport | C527: 1970 | D527: 423 | E527: 65
A528: 311-5 | B528: Remote Control Car Set | C528: 1970 | D528: 365 | E528: 189
A529: 312-1 | B529: Remote Control Unit | C529: 1970 | D529: 371 | E529: 1
A530: 338-1 | B530: Ambulance | C530: 1970 | D530: 420 | E530: 74
A531: 345-3 | B531: House with Mini-Wheel Car | C531: 1970 | D531: 413 | E531: 132
A532: 346-1 | B532: Jumbo Jet | C532: 1970 | D532: 412 | E532: 117
A533: 347-1 | B533: Fire Station with Mini Cars | C533: 1970 | D533: 417 | E533: 206
... A554: WEETABIX1-1 | B554: Weetabix Castle | C554: 1970 | D554: 414 | E554: 471
A555: 45679 | B555: Car | C555: 1971 | D555: 433 | E555: 47
A556: 45680 | B556: Delivery Truck Set | C556: 1971 | D556: 433 | E556: 64
A557: 45681 | B557: Minitalia Train | C557: 1971 | D557: 433 | E557: 77
A558: 45709 | B558: Truck | C558: 1971 | D558: 433 | E558: 33
A559: 45752 | B559: Large House Set | C559: 1971 | D559: 433 | E559: 307
A560: 45872 | B560: Mini-Wheel Model Maker No. 3 | C560: 1971 | D560: 423 | E560: 67
A561: 45931 | B561: Mini-Wheel Model Maker No. 1 | C561: 1971 | D561: 423 | E561: 87
A562: 45932 | B562: Mini-Wheel Model Maker No. 2 | C562: 1971 | D562: 423 | E562: 72
A563: 101-2 | B563: Imagination Set 1 | C563: 1971 | D563: 366 | E563: 298
A564: 103-2 | B564: Imagination Set 3 | C564: 1971 | D564: 366 | E564: 568
A565: 107-3 | B565: 4.5V Reversible Power Unit | C565: 1971 | D565: 371 | E565: 24
A566: 112-3 | B566: 2 40 x 40 Baseplates | C566: 1971 | D566: 301 | E566: 2
A567: 128-3 | B567: Mobile Crane (Plate Base) | C567: 1971 | D567: 235 | E567: 38
A568: 248-2 | B568: Factory With Conveyor Belt | C568: 1971 | D568: 416 | E568: 208
A569: 260-3 | B569: Complete Living Room Set | C569: 1971 | D569: 405 | E569: 177
A570: 261-4 | B570: Complete Kitchen Set | C570: 1971 | D570: 405 | E570: 157
A571: 348-1 | B571: Garage with Automatic Doors | C571: 1971 | D571: 413 | E571: 38
A572: 349-1 | B572: Swiss Chalet | C572: 1971 | D572: 413 | E572: 81
A573: 350-1 | B573: Spanish Villa | C573: 1971 | D573: 413 | E573: 126
A574: 351-1 | B574: Loader Hopper with Truck | C574: 1971 | D574: 416 | E574: 170
... A644: 939-1 | B644: Flags, Trees and Road Signs | C644: 1972 | D644: 473 | E644: 19
A645: 45688 | B645: Medium Ship Set | C645: 1973 | D645: 433 | E645: 39
A646: 45699 | B646: Small Pre-School Basic Set | C646: 1973 | D646: 433 | E646: 31
A647: 45701 | B647: Large Pre-School Basic Set | C647: 1973 | D647: 433 | E647: 92
A648: 45703 | B648: Large House Set | C648: 1973 | D648: 433 | E648: 157
A649: 45720 | B649: Basic Set | C649: 1973 | D649: 469 | E649: 234
A650: 45721 | B650: Basic Set | C650: 1973 | D650: 469 | E650: 330
A651: 45722 | B651: Basic Set | C651: 1973 | D651: 469 | E651: 338
A652: 45723 | B652: Basic Set | C652: 1973 | D652: 469 | E652: 412
A653: 45724 | B653: Basic Set | C653: 1973 | D653: 469 | E653: 665
A654: 45730 | B654: Small house set | C654: 1973 | D654: 433 | E654: 0
A655: 45750 | B655: Basic Set | C655: 1973 | D655: 469 | E655: 191
A656: 45839 | B656: Basic Set | C656: 1973 | D656: 469 | E656: 107
A657: 45840 | B657: Basic Set | C657: 1973 | D657: 469 | E657: 139
A658: 030-2 | B658: Building Set | C658: 1973 | D658: 505 | E658: 29
A659: 105-2 | B659: Building Set | C659: 1973 | D659: 469 | E659: 150
A660: 115-1 | B660: Building Set | C660: 1973 | D660: 469 | E660: 190
A661: 135-1 | B661: Building Set | C661: 1973 | D661: 469 | E661: 338
A662: 221-1 | B662: Idea Book #1 | C662: 1973 | D662: 497 | E662: 0
A663: 270-2 | B663: Grandfather Clock, Chair and Table | C663: 1973 | D663: 405 | E663: 46
A664: 271-1 | B664: Baby's Cot and Cabinet | C664: 1973 | D664: 405 | E664: 48
A665: 272-1 | B665: Dressing Table with Mirror | C665: 1973 | D665: 405 | E665: 31
A666: 273-1 | B666: Bureau | C666: 1973 | D666: 405 | E666: 23
A667: 290-2 | B667: Dining Suite | C667: 1973 | D667: 405 | E667: 113
A668: 291-1 | B668: Blackboard and School Desk | C668: 1973 | D668: 405 | E668: 88
A669: 292-1 | B669: Kitchen Sink and Cupboards | C669: 1973 | D669: 405 | E669: 51
... A792: 814-2 | B792: Gear Farm Set | C792: 1975 | D792: 472 | E792: 88
A793: 45677 | B793: Universal Building Set | C793: 1976 | D793: 469 | E793: 218
A794: 45687 | B794: Universal Building Set | C794: 1976 | D794: 469 | E794: 200
A795: 45698 | B795: Universal Building Set | C795: 1976 | D795: 469 | E795: 129
A796: 45963 | B796: Medium Basic LEGO Set | C796: 1976 | D796: 433 | E796: 130
A797: 074-1 | B797: Pre-School Set | C797: 1976 | D797: 505 | E797: 20
A798: 080-3 | B798: Police Station | C798: 1976 | D798: 505 | E798: 25
...

Sheet set-with-ThemeName
A1: set_num | B1: name | C1: year | D1: theme_id | E1: num_parts | F1: Theme_Name
A2: 700.1-1 | B2: Extra-Large Gift Set (ABB) | C2: 1949 | D2: 365 | E2: 142 | F2: =VLOOKUP(Table13[[#This Row],[theme_id]],'Themes-name-data'!$A$1:$B$597,2,FALSE) -> System
A3: 700.2-1 | B3: Large Gift Set (ABB) | C3: 1949 | D3: 365 | E3: 178 | F3: =VLOOKUP(Table13[[#This Row],[theme_id]],'Themes-name-data'!$A$1:$B$597,2,FALSE) -> System | H3: Theme Name using vlookup
A4: 700.3-1 | B4: Medium Gift Set (ABB) | C4: 1949 | D4: 365 | E4: 142 | F4: =VLOOKUP(Table13[[#This Row],[theme_id]],'Themes-name-data'!$A$1:$B$597,2,FALSE) -> System
A5: 700.A-1 | B5: Small Brick Set (ABB) | C5: 1949 | D5: 371 | E5: 24 | F5: =VLOOKUP(Table13[[#This Row],[theme_id]],'Themes-name-data'!$A$1:$B$597,2,FALSE) -> Supplemental
A6: 700.B-1 | B6: Small Doors and Windows Set (ABB) | C6: 1949 | D6: 371 | E6: 12 | F6: =VLOOKUP(Table13[[#This Row],[theme_id]],'Themes-name-data'!$A$1:$B$597,2,FALSE) -> Supplemental
A7: 700.1.1-1 | B7: Single 2 x 4 Brick (ABB) | C7: 1950 | D7: 371 | E7: 1 | F7: =VLOOKUP(Table13[[#This Row],[theme_id]],'Themes-name-data'!$A$1:$B$597,2,FALSE) -> Supplemental
A8: 700.1.2-1 | B8: Single 2 x 2 Brick (ABB) | C8: 1950 | D8: 371 | E8: 1 | F8: =VLOOKUP(Table13[[#This Row],[theme_id]],'Themes-name-data'!$A$1:$B$597,2,FALSE) -> Supplemental
A9: 700.B.1-1 | B9: Single 1 x 4 x 2 Window without Glass (ABB) | C9: 1950 | D9: 371 | E9: 1 | F9: =VLOOKUP(Table13[[#This Row],[theme_id]],'Themes-name-data'!$A$1:$B$597,2,FALSE) -> Supplemental | J9: data on theme names with the number sets per theme
A10: 700.B.2-1 | B10: Single 1 x 2 x 3 Window without Glass (ABB) | C10: 1950 | D10: 371 | E10: 1 | F10: =VLOOKUP(Table13[[#This Row],[theme_id]],'Themes-name-data'!$A$1:$B$597,2,FALSE) -> Supplemental
A11: 700.B.3-1 | B11: Single 1 x 2 x 2 Window without Glass (ABB) | C11: 1950 | D11: 371 | E11: 1 | F11: =VLOOKUP(Table13[[#This Row],[theme_id]],'Themes-name-data'!$A$1:$B$597,2,FALSE) -> Supplemental | J11: Theme Name | K11: Count of Theme_Name
A12: 700.B.4-1 | B12: Single 1 x 2 x 4 Door without Glass (ABB) | C12: 1950 | D12: 371 | E12: 1 | F12: =VLOOKUP(Table13[[#This Row],[theme_id]],'Themes-name-data'!$A$1:$B$597,2,FALSE) -> Supplemental | J12: Basic Set | K12: 558
A13: 700.1.4-1 | B13: Individual 1 x 2 Bricks | C13: 1953 | D13: 371 | E13: 1 | F13: =VLOOKUP(Table13[[#This Row],[theme_id]],'Themes-name-data'!$A$1:$B$597,2,FALSE) -> Supplemental | J13: Books | K13: 310
A14: 700.1-2 | B14: Extra-Large Gift Set (Mursten) | C14: 1953 | D14: 366 | E14: 0 | F14: =VLOOKUP(Table13[[#This Row],[theme_id]],'Themes-name-data'!$A$1:$B$597,2,FALSE) -> Basic Set | J14: Friends | K14: 415
A15: 700.3.4-1 | B15: Individual 2 x 3 Bricks | C15: 1953 | D15: 371 | E15: 5 | F15: =VLOOKUP(Table13[[#This Row],[theme_id]],'Themes-name-data'!$A$1:$B$597,2,FALSE) -> Supplemental | J15: Gear | K15: 656
A16: 700.F-1 | B16: Automatic Binding Bricks - Small Brick Set (Lego Mursten) | C16: 1953 | D16: 371 | E16: 48 | F16: =VLOOKUP(Table13[[#This Row],[theme_id]],'Themes-name-data'!$A$1:$B$597,2,FALSE) -> Supplemental | J16: Key Chain | K16: 329
A17: 700.16-1 | B17: Individual 2 x 8 Bricks | C17: 1954 | D17: 371 | E17: 5 | F17: =VLOOKUP(Table13[[#This Row],[theme_id]],'Themes-name-data'!$A$1:$B$597,2,FALSE) -> Supplemental | J17: Ninjago | K17: 360
A18: 700.20-1 | B18: Individual 2 x 10 Bricks | C18: 1954 | D18: 371 | E18: 5 | F18: =VLOOKUP(Table13[[#This Row],[theme_id]],'Themes-name-data'!$A$1:$B$597,2,FALSE) -> Supplemental | J18: Star Wars | K18: 776
A19: 700.24-1 | B19: Individual 2 x 12 Bricks | C19: 1954 | D19: 371 | E19: 5 | F19: =VLOOKUP(Table13[[#This Row],[theme_id]],'Themes-name-data'!$A$1:$B$597,2,FALSE) -> Supplemental | J19: Supplemental | K19: 535
A20: 700.28-1 | B20: Individual 2 x 14 Bricks | C20: 1954 | D20: 371 | E20: 5 | F20: =VLOOKUP(Table13[[#This Row],[theme_id]],'Themes-name-data'!$A$1:$B$597,2,FALSE) -> Supplemental | J20: Technic | K20: 453
A21: 700.C.1-1 | B21: Individual 1 x 6 x 4 Panorama Window (with glass) | C21: 1954 | D21: 371 | E21: 4 | F21: =VLOOKUP(Table13[[#This Row],[theme_id]],'Themes-name-data'!$A$1:$B$597,2,FALSE) -> Supplemental | J21: Town | K21: 360
A22: 700.C.2-1 | B22: Individual 1 x 6 x 3 3-Pane Window (with glass) | C22: 1954 | D22: 371 | E22: 4 | F22: =VLOOKUP(Table13[[#This Row],[theme_id]],'Themes-name-data'!$A$1:$B$597,2,FALSE) -> Supplemental | J22: Grand Total | K22: 4752
A23: 700.C.3-1 | B23: Individual 1 x 6 x 3 Shutter Window (with glass) | C23: 1954 | D23: 371 | E23: 4 | F23: =VLOOKUP(Table13[[#This Row],[theme_id]],'Themes-name-data'!$A$1:$B$597,2,FALSE) -> Supplemental
A24: 700.C.4-1 | B24: Individual 1 x 4 x 3 Window (with glass) | C24: 1954 | D24: 371 | E24: 4 | F24: =VLOOKUP(Table13[[#This Row],[theme_id]],'Themes-name-data'!$A$1:$B$597,2,FALSE) -> Supplemental
A25: 700.C.5-1 | B25: Individual 1 x 3 x 3 Window (with glass) | C25: 1954 | D25: 371 | E25: 4 | F25: =VLOOKUP(Table13[[#This Row],[theme_id]],'Themes-name-data'!$A$1:$B$597,2,FALSE) -> Supplemental
A26: 700.C.6-1 | B26: Individual 1 x 2 x 4 Door (with glass) | C26: 1954 | D26: 371 | E26: 4 | F26: =VLOOKUP(Table13[[#This Row],[theme_id]],'Themes-name-data'!$A$1:$B$597,2,FALSE) -> Supplemental
A27: 700.C-1 | B27: Tall Classic Windows/Door (with Glass) | C27: 1954 | D27: 371 | E27: 24 | F27: =VLOOKUP(Table13[[#This Row],[theme_id]],'Themes-name-data'!$A$1:$B$597,2,FALSE) -> Supplemental
A28: 700.H-1 | B28: Individual 4 x 4 Corner Bricks | C28: 1954 | D28: 371 | E28: 5 | F28: =VLOOKUP(Table13[[#This Row],[theme_id]],'Themes-name-data'!$A$1:$B$597,2,FALSE) -> Supplemental
A29: 700GP5-1 | B29: Gift Package (Lego Mursten) | C29: 1954 | D29: 372 | E29: 54 | F29: =VLOOKUP(Table13[[#This Row],[theme_id]],'Themes-name-data'!$A$1:$B$597,2,FALSE) -> Town Plan
A30: 700GP6-1 | B30: Gift Package (Lego Mursten) | C30: 1954 | D30: 372 | E30: 46 | F30: =VLOOKUP(Table13[[#This Row],[theme_id]],'Themes-name-data'!$A$1:$B$597,2,FALSE) -> Town Plan
A31: 1200-1 | B31: LEGO Town Plan Board, Large Plastic | C31: 1955 | D31: 372 | E31: 1 | F31: =VLOOKUP(Table13[[#This Row],[theme_id]],'Themes-name-data'!$A$1:$B$597,2,FALSE) -> Town Plan
A32: 1210-2 | B32: Small Store Set | C32: 1955 | D32: 372 | E32: 30 | F32: =VLOOKUP(Table13[[#This Row],[theme_id]],'Themes-name-data'!$A$1:$B$597,2,FALSE) -> Town Plan
A33: 1211-2 | B33: Small House Set | C33: 1955 | D33: 372 | E33: 19 | F33: =VLOOKUP(Table13[[#This Row],[theme_id]],'Themes-name-data'!$A$1:$B$597,2,FALSE) -> Town Plan
A34: 1212-2 | B34: Small House - Left Set | C34: 1955 | D34: 372 | E34: 21 | F34: =VLOOKUP(Table13[[#This Row],[theme_id]],'Themes-name-data'!$A$1:$B$597,2,FALSE) -> Town Plan
... A369: b66de-01 | B369: LEGO Motor Eisenbahn | C369: 1966 | D369: 499 | E369: 0 | F369: =VLOOKUP(Table13[[#This Row],[theme_id]],'Themes-name-data'!$A$1:$B$597,2,FALSE) -> Train
A370: 45692 | B370: Velveeta Set No. 4 with Carrying Case | C370: 1967 | D370: 366 | E370: 283 | F370: =VLOOKUP(Table13[[#This Row],[theme_id]],'Themes-name-data'!$A$1:$B$597,2,FALSE) -> Basic Set
A371: 45693 | B371: Velveeta Set No. 5 | C371: 1967 | D371: 371 | E371: 20 | F371: =VLOOKUP(Table13[[#This Row],[theme_id]],'Themes-name-data'!$A$1:$B$597,2,FALSE) -> Supplemental
A372: 45717 | B372: Velveeta Set No. 1 | C372: 1967 | D372: 366 | E372: 74 | F372: =VLOOKUP(Table13[[#This Row],[theme_id]],'Themes-name-data'!$A$1:$B$597,2,FALSE) -> Basic Set
A373: 005-2 | B373: Discovery Set | C373: 1967 | D373: 366 | E373: 0 | F373: =VLOOKUP(Table13[[#This Row],[theme_id]],'Themes-name-data'!$A$1:$B$597,2,FALSE) -> Basic Set
A374: 080-1 | B374: Basic Building Set with Train | C374: 1967 | D374: 366 | E374: 712 | F374: =VLOOKUP(Table13[[#This Row],[theme_id]],'Themes-name-data'!$A$1:$B$597,2,FALSE) -> Basic Set
A375: 080-2 | B375: Ambassador Set | C375: 1967 | D375: 366 | E375: 712 | F375: =VLOOKUP(Table13[[#This Row],[theme_id]],'Themes-name-data'!$A$1:$B$597,2,FALSE) -> Basic Set
A376: 116-1 | B376: Starter Train Set with Motor | C376: 1967 | D376: 235 | E376: 364 | F376: =VLOOKUP(Table13[[#This Row],[theme_id]],'Themes-name-data'!$A$1:$B$597,2,FALSE) -> 4.5V
A377: 117-1 | B377: Locomotive without Motor | C377: 1967 | D377: 235 | E377: 99 | F377: =VLOOKUP(Table13[[#This Row],[theme_id]],'Themes-name-data'!$A$1:$B$597,2,FALSE) -> 4.5V
A378: 154-1 | B378: Switch Track - 1 Right and 1 Left | C378: 1967 | D378: 243 | E378: 4 | F378: =VLOOKUP(Table13[[#This Row],[theme_id]],'Themes-name-data'!$A$1:$B$597,2,FALSE) -> 4.5V
A379: 155-1 | B379: 2 Cross Rails, 8 Straight Tracks, 4 Base Plates | C379: 1967 | D379: 243 | E379: 14 | F379: =VLOOKUP(Table13[[#This Row],[theme_id]],'Themes-name-data'!$A$1:$B$597,2,FALSE) -> 4.5V
A380: 240-1 | B380: Wooden Storage Box Large, Empty | C380: 1967 | D380: 383 | E380: 0 | F380: =VLOOKUP(Table13[[#This Row],[theme_id]],'Themes-name-data'!$A$1:$B$597,2,FALSE) -> Wooden Box Set
A381: 240-2 | B381: Idea Book | C381: 1967 | D381: 497 | E381: 1 | F381: =VLOOKUP(Table13[[#This Row],[theme_id]],'Themes-name-data'!$A$1:$B$597,2,FALSE) -> Books
A382: 328-2 | B382: Biplane | C382: 1967 | D382: 374 | E382: 44 | F382: =VLOOKUP(Table13[[#This Row],[theme_id]],'Themes-name-data'!$A$1:$B$597,2,FALSE) -> Airport
A383: 329-1 | B383: Antique Car | C383: 1967 | D383: 378 | E383: 111 | F383: =VLOOKUP(Table13[[#This Row],[theme_id]],'Themes-name-data'!$A$1:$B$597,2,FALSE) -> Traffic
A384: 331-1 | B384: Dump Truck | C384: 1967 | D384: 381 | E384: 45 | F384: =VLOOKUP(Table13[[#This Row],[theme_id]],'Themes-name-data'!$A$1:$B$597,2,FALSE) -> Construction
... A517: LIFECEREAL-1 | B517: Puppet Set | C517: 1969 | D517: 598 | E517: 92 | F517: =VLOOKUP(Table13[[#This Row],[theme_id]],'Themes-name-data'!$A$1:$B$597,2,FALSE) -> Promotional
A518: 45751 | B518: Large House Set | C518: 1970 | D518: 433 | E518: 218 | F518: =VLOOKUP(Table13[[#This Row],[theme_id]],'Themes-name-data'!$A$1:$B$597,2,FALSE) -> Minitalia
A519: 45811 | B519: Medium House Set | C519: 1970 | D519: 433 | E519: 158 | F519: =VLOOKUP(Table13[[#This Row],[theme_id]],'Themes-name-data'!$A$1:$B$597,2,FALSE) -> Minitalia
A520: 45870 | B520: Little House Set | C520: 1970 | D520: 433 | E520: 67 | F520: =VLOOKUP(Table13[[#This Row],[theme_id]],'Themes-name-data'!$A$1:$B$597,2,FALSE) -> Minitalia
A521: 45871 | B521: Medium House Set | C521: 1970 | D521: 433 | E521: 109 | F521: =VLOOKUP(Table13[[#This Row],[theme_id]],'Themes-name-data'!$A$1:$B$597,2,FALSE) -> Minitalia
A522: 078-1 | B522: Roadway Base Plate | C522: 1970 | D522: 371 | E522: 0 | F522: =VLOOKUP(Table13[[#This Row],[theme_id]],'Themes-name-data'!$A$1:$B$597,2,FALSE) -> Supplemental
A523: 102A-1 | B523: Front-End Loader | C523: 1970 | D523: 416 | E523: 64 | F523: =VLOOKUP(Table13[[#This Row],[theme_id]],'Themes-name-data'!$A$1:$B$597,2,FALSE) -> Construction
A524: 102A-2 | B524: Front-End Loader | C524: 1970 | D524: 416 | E524: 56 | F524: =VLOOKUP(Table13[[#This Row],[theme_id]],'Themes-name-data'!$A$1:$B$597,2,FALSE) -> Construction
A525: 104-1 | B525: Replacement 4.5V Motor | C525: 1970 | D525: 243 | E525: 1 | F525: =VLOOKUP(Table13[[#This Row],[theme_id]],'Themes-name-data'!$A$1:$B$597,2,FALSE) -> 4.5V
A526: 126-1 | B526: Steam Locomotive (Push) | C526: 1970 | D526: 235 | E526: 60 | F526: =VLOOKUP(Table13[[#This Row],[theme_id]],'Themes-name-data'!$A$1:$B$597,2,FALSE) -> 4.5V
A527: 157-3 | B527: Four Car Auto Transport | C527: 1970 | D527: 423 | E527: 65 | F527: =VLOOKUP(Table13[[#This Row],[theme_id]],'Themes-name-data'!$A$1:$B$597,2,FALSE) -> Vehicle
A528: 311-5 | B528: Remote Control Car Set | C528: 1970 | D528: 365 | E528: 189 | F528: =VLOOKUP(Table13[[#This Row],[theme_id]],'Themes-name-data'!$A$1:$B$597,2,FALSE) -> System
A529: 312-1 | B529: Remote Control Unit | C529: 1970 | D529: 371 | E529: 1 | F529: =VLOOKUP(Table13[[#This Row],[theme_id]],'Themes-name-data'!$A$1:$B$597,2,FALSE) -> Supplemental
A530: 338-1 | B530: Ambulance | C530: 1970 | D530: 420 | E530: 74 | F530: =VLOOKUP(Table13[[#This Row],[theme_id]],'Themes-name-data'!$A$1:$B$597,2,FALSE) -> Hospital
A531: 345-3 | B531: House with Mini-Wheel Car | C531: 1970 | D531: 413 | E531: 132 | F531: =VLOOKUP(Table13[[#This Row],[theme_id]],'Themes-name-data'!$A$1:$B$597,2,FALSE) -> Building
A532: 346-1 | B532: Jumbo Jet | C532: 1970 | D532: 412 | E532: 117 | F532: =VLOOKUP(Table13[[#This Row],[theme_id]],'Themes-name-data'!$A$1:$B$597,2,FALSE) -> Airport
A533: 347-1 | B533: Fire Station with Mini Cars | C533: 1970 | D533: 417 | E533: 206 | F533: =VLOOKUP(Table13[[#This Row],[theme_id]],'Themes-name-data'!$A$1:$B$597,2,FALSE) -> Fire
... A554: WEETABIX1-1 | B554: Weetabix Castle | C554: 1970 | D554: 414 | E554: 471 | F554: =VLOOKUP(Table13[[#This Row],[theme_id]],'Themes-name-data'!$A$1:$B$597,2,FALSE) -> Castle
A555: 45679 | B555: Car | C555: 1971 | D555: 433 | E555: 47 | F555: =VLOOKUP(Table13[[#This Row],[theme_id]],'Themes-name-data'!$A$1:$B$597,2,FALSE) -> Minitalia
A556: 45680 | B556: Delivery Truck Set | C556: 1971 | D556: 433 | E556: 64 | F556: =VLOOKUP(Table13[[#This Row],[theme_id]],'Themes-name-data'!$A$1:$B$597,2,FALSE) -> Minitalia
A557: 45681 | B557: Minitalia Train | C557: 1971 | D557: 433 | E557: 77 | F557: =VLOOKUP(Table13[[#This Row],[theme_id]],'Themes-name-data'!$A$1:$B$597,2,FALSE) -> Minitalia
A558: 45709 | B558: Truck | C558: 1971 | D558: 433 | E558: 33 | F558: =VLOOKUP(Table13[[#This Row],[theme_id]],'Themes-name-data'!$A$1:$B$597,2,FALSE) -> Minitalia
A559: 45752 | B559: Large House Set | C559: 1971 | D559: 433 | E559: 307 | F559: =VLOOKUP(Table13[[#This Row],[theme_id]],'Themes-name-data'!$A$1:$B$597,2,FALSE) -> Minitalia
A560: 45872 | B560: Mini-Wheel Model Maker No. 3 | C560: 1971 | D560: 423 | E560: 67 | F560: =VLOOKUP(Table13[[#This Row],[theme_id]],'Themes-name-data'!$A$1:$B$597,2,FALSE) -> Vehicle
A561: 45931 | B561: Mini-Wheel Model Maker No. 1 | C561: 1971 | D561: 423 | E561: 87 | F561: =VLOOKUP(Table13[[#This Row],[theme_id]],'Themes-name-data'!$A$1:$B$597,2,FALSE) -> Vehicle
A562: 45932 | B562: Mini-Wheel Model Maker No. 2 | C562: 1971 | D562: 423 | E562: 72 | F562: =VLOOKUP(Table13[[#This Row],[theme_id]],'Themes-name-data'!$A$1:$B$597,2,FALSE) -> Vehicle
A563: 101-2 | B563: Imagination Set 1 | C563: 1971 | D563: 366 | E563: 298 | F563: =VLOOKUP(Table13[[#This Row],[theme_id]],'Themes-name-data'!$A$1:$B$597,2,FALSE) -> Basic Set
A564: 103-2 | B564: Imagination Set 3 | C564: 1971 | D564: 366 | E564: 568 | F564: =VLOOKUP(Table13[[#This Row],[theme_id]],'Themes-name-data'!$A$1:$B$597,2,FALSE) -> Basic Set
A565: 107-3 | B565: 4.5V Reversible Power Unit | C565: 1971 | D565: 371 | E565: 24 | F565: =VLOOKUP(Table13[[#This Row],[theme_id]],'Themes-name-data'!$A$1:$B$597,2,FALSE) -> Supplemental
A566: 112-3 | B566: 2 40 x 40 Baseplates | C566: 1971 | D566: 301 | E566: 2 | F566: =VLOOKUP(Table13[[#This Row],[theme_id]],'Themes-name-data'!$A$1:$B$597,2,FALSE) -> Other
A567: 128-3 | B567: Mobile Crane (Plate Base) | C567: 1971 | D567: 235 | E567: 38 | F567: =VLOOKUP(Table13[[#This Row],[theme_id]],'Themes-name-data'!$A$1:$B$597,2,FALSE) -> 4.5V
A568: 248-2 | B568: Factory With Conveyor Belt | C568: 1971 | D568: 416 | E568: 208 | F568: =VLOOKUP(Table13[[#This Row],[theme_id]],'Themes-name-data'!$A$1:$B$597,2,FALSE) -> Construction
A569: 260-3 | B569: Complete Living Room Set | C569: 1971 | D569: 405 | E569: 177 | F569: =VLOOKUP(Table13[[#This Row],[theme_id]],'Themes-name-data'!$A$1:$B$597,2,FALSE) -> Homemaker
A570: 261-4 | B570: Complete Kitchen Set | C570: 1971 | D570: 405 | E570: 157 | F570: =VLOOKUP(Table13[[#This Row],[theme_id]],'Themes-name-data'!$A$1:$B$597,2,FALSE) -> Homemaker
A571: 348-1 | B571: Garage with Automatic Doors | C571: 1971 | D571: 413 | E571: 38 | F571: =VLOOKUP(Table13[[#This Row],[theme_id]],'Themes-name-data'!$A$1:$B$597,2,FALSE) -> Building
A572: 349-1 | B572: Swiss Chalet | C572: 1971 | D572: 413 | E572: 81 | F572: =VLOOKUP(Table13[[#This Row],[theme_id]],'Themes-name-data'!$A$1:$B$597,2,FALSE) -> Building
A573: 350-1 | B573: Spanish Villa | C573: 1971 | D573: 413 | E573: 126 | F573: =VLOOKUP(Table13[[#This Row],[theme_id]],'Themes-name-data'!$A$1:$B$597,2,FALSE) -> Building
A574: 351-1 | B574: Loader Hopper with Truck | C574: 1971 | D574: 416 | E574: 170 | F574: =VLOOKUP(Table13[[#This Row],[theme_id]],'Themes-name-data'!$A$1:$B$597,2,FALSE) -> Construction
... A644: 939-1 | B644: Flags, Trees and Road Signs | C644: 1972 | D644: 473 | E644: 19 | F644: =VLOOKUP(Table13[[#This Row],[theme_id]],'Themes-name-data'!$A$1:$B$597,2,FALSE) -> Supplemental
A645: 45688 | B645: Medium Ship Set | C645: 1973 | D645: 433 | E645: 39 | F645: =VLOOKUP(Table13[[#This Row],[theme_id]],'Themes-name-data'!$A$1:$B$597,2,FALSE) -> Minitalia
A646: 45699 | B646: Small Pre-School Basic Set | C646: 1973 | D646: 433 | E646: 31 | F646: =VLOOKUP(Table13[[#This Row],[theme_id]],'Themes-name-data'!$A$1:$B$597,2,FALSE) -> Minitalia
A647: 45701 | B647: Large Pre-School Basic Set | C647: 1973 | D647: 433 | E647: 92 | F647: =VLOOKUP(Table13[[#This Row],[theme_id]],'Themes-name-data'!$A$1:$B$597,2,FALSE) -> Minitalia
A648: 45703 | B648: Large House Set | C648: 1973 | D648: 433 | E648: 157 | F648: =VLOOKUP(Table13[[#This Row],[theme_id]],'Themes-name-data'!$A$1:$B$597,2,FALSE) -> Minitalia
A649: 45720 | B649: Basic Set | C649: 1973 | D649: 469 | E649: 234 | F649: =VLOOKUP(Table13[[#This Row],[theme_id]],'Themes-name-data'!$A$1:$B$597,2,FALSE) -> Basic Set
A650: 45721 | B650: Basic Set | C650: 1973 | D650: 469 | E650: 330 | F650: =VLOOKUP(Table13[[#This Row],[theme_id]],'Themes-name-data'!$A$1:$B$597,2,FALSE) -> Basic Set
A651: 45722 | B651: Basic Set | C651: 1973 | D651: 469 | E651: 338 | F651: =VLOOKUP(Table13[[#This Row],[theme_id]],'Themes-name-data'!$A$1:$B$597,2,FALSE) -> Basic Set
A652: 45723 | B652: Basic Set | C652: 1973 | D652: 469 | E652: 412 | F652: =VLOOKUP(Table13[[#This Row],[theme_id]],'Themes-name-data'!$A$1:$B$597,2,FALSE) -> Basic Set
A653: 45724 | B653: Basic Set | C653: 1973 | D653: 469 | E653: 665 | F653: =VLOOKUP(Table13[[#This Row],[theme_id]],'Themes-name-data'!$A$1:$B$597,2,FALSE) -> Basic Set
A654: 45730 | B654: Small house set | C654: 1973 | D654: 433 | E654: 0 | F654: =VLOOKUP(Table13[[#This Row],[theme_id]],'Themes-name-data'!$A$1:$B$597,2,FALSE) -> Minitalia
A655: 45750 | B655: Basic Set | C655: 1973 | D655: 469 | E655: 191 | F655: =VLOOKUP(Table13[[#This Row],[theme_id]],'Themes-name-data'!$A$1:$B$597,2,FALSE) -> Basic Set
...
